{"nodes":[{"id":0},{"id":1},{"id":2},{"id":3},{"id":4},{"id":5},{"id":6},{"id":7},{"id":8},{"id":9},{"id":10},{"id":11},{"id":12},{"id":13},{"id":14},{"id":15},{"id":16},{"id":17},{"id":18},{"id":19}],"edges":[{"source":9,"target":2},{"source":11,"target":19},{"source":17,"target":0},{"source":16,"target":3},{"source":19,"target":12},{"source":2,"target":0},{"source":12,"target":18},{"source":18,"target":4},{"source":12,"target":9},{"source":19,"target":16},{"source":1,"target":14},{"source":2,"target":11},{"source":4,"target":10},{"source":7,"target":16},{"source":4,"target":6},{"source":3,"target":13},{"source":6,"target":11},{"source":6,"target":2},{"source":10,"target":19},{"source":12,"target":16},{"source":17,"target":2},{"source":7,"target":9},{"source":5,"target":4},{"source":13,"target":8},{"source":0,"target":5},{"source":5,"target":7},{"source":8,"target":11},{"source":14,"target":5},{"source":7,"target":1},{"source":4,"target":3},{"source":15,"target":8},{"source":0,"target":3},{"source":12,"target":8},{"source":3,"target":5},{"source":5,"target":2},{"source":18,"target":1},{"source":1,"target":16},{"source":7,"target":19},{"source":1,"target":9},{"source":10,"target":2},{"source":4,"target":1},{"source":18,"target":6},{"source":6,"target":19},{"source":9,"target":4},{"source":16,"target":9},{"source":5,"target":19},{"source":17,"target":1},{"source":2,"target":14},{"source":1,"target":5},{"source":19,"target":0},{"source":9,"target":18},{"source":16,"target":6},{"source":3,"target":9},{"source":15,"target":11},{"source":5,"target":18},{"source":3,"target":14},{"source":8,"target":0},{"source":3,"target":1},{"source":5,"target":15},{"source":9,"target":14},{"source":10,"target":12},{"source":18,"target":16},{"source":13,"target":1},{"source":9,"target":6},{"source":6,"target":10},{"source":12,"target":4},{"source":19,"target":8},{"source":11,"target":9},{"source":14,"target":18},{"source":4,"target":2},{"source":10,"target":15},{"source":0,"target":15},{"source":16,"target":2},{"source":8,"target":18},{"source":7,"target":2},{"source":13,"target":10},{"source":11,"target":14},{"source":17,"target":15},{"source":0,"target":18},{"source":3,"target":12},{"source":5,"target":9},{"source":11,"target":1},{"source":1,"target":10},{"source":11,"target":13},{"source":3,"target":11},{"source":3,"target":10},{"source":12,"target":7},{"source":19,"target":18},{"source":11,"target":12},{"source":7,"target":6},{"source":5,"target":16},{"source":18,"target":17},{"source":0,"target":6},{"source":17,"target":8},{"source":1,"target":8},{"source":19,"target":15},{"source":10,"target":18},{"source":14,"target":17},{"source":13,"target":15},{"source":17,"target":4},{"source":8,"target":14},{"source":4,"target":16},{"source":19,"target":9},{"source":0,"target":1},{"source":3,"target":7},{"source":18,"target":13},{"source":2,"target":19},{"source":14,"target":6},{"source":7,"target":10},{"source":2,"target":15},{"source":2,"target":1},{"source":11,"target":0},{"source":11,"target":5},{"source":5,"target":13}],"width":189,"points":[{"x":18,"y":57,"id":0},{"x":114,"y":140,"id":1},{"x":171,"y":125,"id":2},{"x":62,"y":78,"id":3},{"x":1,"y":141,"id":4},{"x":183,"y":63,"id":5},{"x":169,"y":43,"id":6},{"x":121,"y":171,"id":7},{"x":173,"y":126,"id":8},{"x":147,"y":32,"id":9},{"x":26,"y":129,"id":10},{"x":112,"y":32,"id":11},{"x":182,"y":147,"id":12},{"x":19,"y":65,"id":13},{"x":154,"y":122,"id":14},{"x":123,"y":18,"id":15},{"x":181,"y":33,"id":16},{"x":122,"y":60,"id":17},{"x":92,"y":20,"id":18},{"x":69,"y":32,"id":19},{"x":119,"y":186,"id":20},{"x":41,"y":85,"id":21},{"x":44,"y":46,"id":22},{"x":113,"y":8,"id":23},{"x":78,"y":150,"id":24},{"x":19,"y":127,"id":25},{"x":66,"y":3,"id":26},{"x":162,"y":182,"id":27},{"x":51,"y":37,"id":28},{"x":141,"y":177,"id":29},{"x":165,"y":22,"id":30},{"x":149,"y":39,"id":31},{"x":152,"y":13,"id":32},{"x":175,"y":21,"id":33},{"x":173,"y":78,"id":34},{"x":157,"y":120,"id":35},{"x":26,"y":20,"id":36},{"x":167,"y":147,"id":37},{"x":108,"y":67,"id":38},{"x":48,"y":139,"id":39},{"x":25,"y":74,"id":40},{"x":89,"y":113,"id":41},{"x":163,"y":17,"id":42},{"x":35,"y":133,"id":43},{"x":12,"y":25,"id":44},{"x":150,"y":134,"id":45},{"x":29,"y":130,"id":46},{"x":96,"y":153,"id":47},{"x":94,"y":108,"id":48},{"x":135,"y":143,"id":49},{"x":65,"y":30,"id":50},{"x":8,"y":64,"id":51},{"x":117,"y":120,"id":52},{"x":177,"y":2,"id":53},{"x":82,"y":26,"id":54},{"x":5,"y":116,"id":55},{"x":170,"y":21,"id":56},{"x":52,"y":155,"id":57},{"x":40,"y":185,"id":58},{"x":156,"y":46,"id":59}],"height":189}