{"nodes":[{"id":0},{"id":1},{"id":2},{"id":3},{"id":4},{"id":5},{"id":6},{"id":7},{"id":8},{"id":9},{"id":10},{"id":11},{"id":12},{"id":13},{"id":14},{"id":15},{"id":16},{"id":17},{"id":18},{"id":19},{"id":20},{"id":21},{"id":22},{"id":23},{"id":24},{"id":25},{"id":26},{"id":27},{"id":28},{"id":29},{"id":30},{"id":31},{"id":32},{"id":33},{"id":34},{"id":35},{"id":36},{"id":37},{"id":38},{"id":39},{"id":40},{"id":41},{"id":42},{"id":43},{"id":44},{"id":45},{"id":46},{"id":47},{"id":48},{"id":49},{"id":50},{"id":51},{"id":52},{"id":53},{"id":54},{"id":55}],"edges":[{"source":12,"target":15},{"source":12,"target":45},{"source":30,"target":8},{"source":32,"target":2},{"source":11,"target":8},{"source":38,"target":46},{"source":20,"target":13},{"source":31,"target":19},{"source":10,"target":54},{"source":7,"target":26},{"source":41,"target":42},{"source":13,"target":22},{"source":41,"target":32},{"source":22,"target":27},{"source":2,"target":0},{"source":36,"target":31},{"source":19,"target":16},{"source":32,"target":54},{"source":55,"target":20},{"source":41,"target":44},{"source":14,"target":13},{"source":15,"target":50},{"source":11,"target":49},{"source":9,"target":12},{"source":15,"target":35},{"source":31,"target":18},{"source":25,"target":9},{"source":13,"target":50},{"source":24,"target":28},{"source":7,"target":13},{"source":8,"target":17},{"source":51,"target":34},{"source":40,"target":37},{"source":36,"target":55},{"source":5,"target":1},{"source":21,"target":42},{"source":10,"target":6},{"source":18,"target":47},{"source":27,"target":16},{"source":38,"target":26},{"source":46,"target":42},{"source":14,"target":34},{"source":19,"target":34},{"source":6,"target":42},{"source":17,"target":36},{"source":29,"target":36},{"source":30,"target":34},{"source":31,"target":7},{"source":26,"target":32},{"source":55,"target":31},{"source":25,"target":21},{"source":39,"target":27},{"source":3,"target":46},{"source":54,"target":49},{"source":2,"target":21},{"source":44,"target":38},{"source":55,"target":7},{"source":53,"target":26},{"source":10,"target":12},{"source":47,"target":15},{"source":28,"target":23},{"source":2,"target":35},{"source":2,"target":44},{"source":12,"target":43},{"source":24,"target":1},{"source":30,"target":15},{"source":8,"target":37},{"source":46,"target":6},{"source":25,"target":29},{"source":25,"target":15},{"source":53,"target":19},{"source":32,"target":6},{"source":6,"target":3},{"source":41,"target":31},{"source":35,"target":4},{"source":17,"target":45},{"source":29,"target":43},{"source":0,"target":21},{"source":20,"target":31},{"source":43,"target":23},{"source":25,"target":17},{"source":13,"target":44},{"source":16,"target":4},{"source":54,"target":3},{"source":48,"target":29},{"source":3,"target":35},{"source":43,"target":38},{"source":45,"target":43},{"source":46,"target":14},{"source":5,"target":30},{"source":40,"target":47},{"source":34,"target":44},{"source":8,"target":28},{"source":55,"target":40},{"source":15,"target":29},{"source":26,"target":49},{"source":4,"target":24},{"source":47,"target":32},{"source":19,"target":45},{"source":36,"target":15},{"source":52,"target":54},{"source":17,"target":27},{"source":38,"target":30},{"source":35,"target":14},{"source":24,"target":45},{"source":2,"target":54},{"source":38,"target":12},{"source":7,"target":9},{"source":9,"target":13},{"source":54,"target":34},{"source":11,"target":28},{"source":5,"target":0},{"source":20,"target":22},{"source":21,"target":19},{"source":5,"target":18},{"source":27,"target":51},{"source":47,"target":19},{"source":37,"target":1},{"source":29,"target":27},{"source":11,"target":43},{"source":16,"target":20},{"source":42,"target":55},{"source":55,"target":38},{"source":6,"target":27},{"source":42,"target":52},{"source":10,"target":16},{"source":5,"target":17},{"source":31,"target":42},{"source":41,"target":23},{"source":14,"target":10},{"source":13,"target":21},{"source":28,"target":3},{"source":23,"target":24},{"source":33,"target":27},{"source":48,"target":44},{"source":8,"target":25},{"source":30,"target":39},{"source":51,"target":18},{"source":2,"target":50},{"source":5,"target":44},{"source":17,"target":34},{"source":14,"target":49},{"source":46,"target":36},{"source":44,"target":4},{"source":40,"target":33},{"source":46,"target":43},{"source":49,"target":29},{"source":26,"target":52},{"source":22,"target":11},{"source":6,"target":39},{"source":23,"target":31},{"source":33,"target":9},{"source":47,"target":35},{"source":55,"target":6},{"source":41,"target":39},{"source":51,"target":16},{"source":40,"target":29},{"source":20,"target":19},{"source":17,"target":52},{"source":50,"target":26},{"source":1,"target":7},{"source":48,"target":53},{"source":3,"target":23},{"source":32,"target":21},{"source":47,"target":16},{"source":12,"target":7},{"source":16,"target":32},{"source":39,"target":20},{"source":5,"target":10},{"source":27,"target":46},{"source":4,"target":22},{"source":42,"target":22},{"source":11,"target":16},{"source":49,"target":4},{"source":36,"target":24},{"source":7,"target":51},{"source":51,"target":44},{"source":2,"target":45},{"source":37,"target":39},{"source":35,"target":31},{"source":50,"target":47},{"source":9,"target":18},{"source":18,"target":46},{"source":55,"target":11},{"source":33,"target":8},{"source":44,"target":3},{"source":23,"target":7},{"source":48,"target":31},{"source":42,"target":19},{"source":53,"target":31},{"source":28,"target":49},{"source":50,"target":43},{"source":28,"target":52},{"source":51,"target":6},{"source":14,"target":55},{"source":22,"target":23},{"source":31,"target":12},{"source":37,"target":7},{"source":19,"target":35},{"source":18,"target":50},{"source":49,"target":44},{"source":21,"target":22},{"source":0,"target":45},{"source":7,"target":42},{"source":12,"target":55},{"source":44,"target":29},{"source":11,"target":21},{"source":5,"target":47},{"source":5,"target":40},{"source":48,"target":46},{"source":48,"target":25},{"source":9,"target":27},{"source":36,"target":47},{"source":19,"target":7},{"source":6,"target":2},{"source":24,"target":48},{"source":52,"target":6},{"source":6,"target":7},{"source":54,"target":28},{"source":33,"target":45},{"source":11,"target":42},{"source":1,"target":39},{"source":17,"target":48},{"source":11,"target":54},{"source":53,"target":44},{"source":28,"target":0},{"source":25,"target":28},{"source":1,"target":10},{"source":45,"target":53},{"source":41,"target":22},{"source":24,"target":3},{"source":30,"target":12},{"source":20,"target":37},{"source":13,"target":31},{"source":22,"target":31},{"source":28,"target":12},{"source":24,"target":44},{"source":38,"target":34},{"source":54,"target":51},{"source":23,"target":40},{"source":4,"target":2},{"source":45,"target":42},{"source":53,"target":27},{"source":2,"target":29},{"source":47,"target":46},{"source":46,"target":20},{"source":37,"target":2},{"source":52,"target":32},{"source":48,"target":12},{"source":29,"target":33},{"source":30,"target":16},{"source":37,"target":10},{"source":40,"target":21},{"source":2,"target":18},{"source":44,"target":39},{"source":22,"target":50},{"source":44,"target":8},{"source":32,"target":36},{"source":51,"target":47},{"source":14,"target":32},{"source":18,"target":10},{"source":45,"target":27},{"source":20,"target":27},{"source":0,"target":7},{"source":48,"target":4},{"source":20,"target":36},{"source":54,"target":39},{"source":27,"target":30},{"source":26,"target":12},{"source":15,"target":9},{"source":50,"target":32},{"source":34,"target":53},{"source":7,"target":45},{"source":18,"target":52},{"source":41,"target":43},{"source":54,"target":53},{"source":21,"target":26},{"source":14,"target":12},{"source":53,"target":38},{"source":6,"target":37},{"source":25,"target":41},{"source":44,"target":55},{"source":19,"target":49},{"source":55,"target":17},{"source":24,"target":19},{"source":53,"target":49},{"source":24,"target":10},{"source":16,"target":46},{"source":10,"target":55},{"source":5,"target":16},{"source":49,"target":24},{"source":18,"target":3},{"source":37,"target":23},{"source":8,"target":19},{"source":43,"target":37},{"source":42,"target":33},{"source":40,"target":3},{"source":29,"target":52},{"source":53,"target":11},{"source":26,"target":6},{"source":10,"target":32},{"source":17,"target":33},{"source":36,"target":9},{"source":14,"target":37},{"source":53,"target":22},{"source":0,"target":8},{"source":22,"target":25},{"source":39,"target":18},{"source":18,"target":34},{"source":52,"target":55},{"source":7,"target":34},{"source":12,"target":36},{"source":52,"target":2},{"source":39,"target":24},{"source":10,"target":4},{"source":6,"target":47},{"source":13,"target":33},{"source":19,"target":15},{"source":30,"target":48},{"source":55,"target":34},{"source":51,"target":45},{"source":48,"target":21},{"source":45,"target":8},{"source":43,"target":13},{"source":48,"target":49},{"source":1,"target":42},{"source":31,"target":38},{"source":8,"target":35},{"source":35,"target":5},{"source":17,"target":49},{"source":16,"target":6},{"source":0,"target":39},{"source":1,"target":19},{"source":34,"target":25},{"source":36,"target":44},{"source":24,"target":40},{"source":1,"target":33},{"source":9,"target":2},{"source":23,"target":19},{"source":31,"target":28},{"source":55,"target":15},{"source":55,"target":3},{"source":34,"target":12},{"source":19,"target":44},{"source":19,"target":9},{"source":25,"target":52},{"source":13,"target":36},{"source":10,"target":15},{"source":32,"target":39},{"source":10,"target":21},{"source":34,"target":20},{"source":1,"target":3},{"source":21,"target":43},{"source":11,"target":39},{"source":8,"target":7},{"source":55,"target":41},{"source":51,"target":29},{"source":21,"target":24},{"source":35,"target":29},{"source":25,"target":16},{"source":44,"target":28},{"source":8,"target":24},{"source":32,"target":53},{"source":41,"target":15},{"source":18,"target":27},{"source":37,"target":42},{"source":33,"target":24},{"source":21,"target":4},{"source":29,"target":23},{"source":40,"target":13},{"source":51,"target":52},{"source":45,"target":28},{"source":42,"target":51},{"source":53,"target":47},{"source":43,"target":33},{"source":34,"target":42},{"source":12,"target":50},{"source":34,"target":3},{"source":35,"target":37},{"source":10,"target":41},{"source":33,"target":30},{"source":27,"target":11},{"source":39,"target":4},{"source":49,"target":45},{"source":45,"target":14},{"source":49,"target":38},{"source":18,"target":32},{"source":30,"target":2},{"source":3,"target":2},{"source":5,"target":33},{"source":11,"target":51},{"source":6,"target":14},{"source":5,"target":11},{"source":16,"target":21},{"source":12,"target":25},{"source":9,"target":38},{"source":16,"target":33},{"source":21,"target":5},{"source":55,"target":22},{"source":17,"target":18},{"source":29,"target":0},{"source":26,"target":48},{"source":9,"target":3},{"source":54,"target":1},{"source":31,"target":34},{"source":50,"target":46},{"source":0,"target":35},{"source":13,"target":3},{"source":17,"target":39},{"source":45,"target":25},{"source":9,"target":29},{"source":7,"target":49},{"source":23,"target":11},{"source":15,"target":48},{"source":14,"target":5},{"source":53,"target":52},{"source":19,"target":27},{"source":3,"target":5},{"source":32,"target":38},{"source":54,"target":7},{"source":39,"target":13},{"source":26,"target":23},{"source":16,"target":3},{"source":25,"target":55},{"source":44,"target":33},{"source":2,"target":47},{"source":0,"target":19},{"source":4,"target":13},{"source":54,"target":43},{"source":47,"target":38},{"source":53,"target":14},{"source":15,"target":11},{"source":46,"target":44},{"source":49,"target":51},{"source":0,"target":41},{"source":17,"target":21},{"source":52,"target":7},{"source":24,"target":46},{"source":51,"target":2},{"source":23,"target":15},{"source":52,"target":33},{"source":33,"target":37},{"source":45,"target":22},{"source":40,"target":26},{"source":12,"target":52},{"source":35,"target":7},{"source":18,"target":30},{"source":48,"target":23},{"source":30,"target":21},{"source":32,"target":34},{"source":20,"target":43},{"source":24,"target":54},{"source":34,"target":10},{"source":13,"target":17},{"source":4,"target":5},{"source":15,"target":37},{"source":47,"target":24},{"source":36,"target":2},{"source":19,"target":17},{"source":45,"target":39},{"source":37,"target":18},{"source":54,"target":31},{"source":44,"target":14},{"source":43,"target":48},{"source":42,"target":3},{"source":10,"target":51},{"source":20,"target":15},{"source":39,"target":40},{"source":3,"target":17},{"source":24,"target":27},{"source":51,"target":37},{"source":26,"target":55},{"source":47,"target":13},{"source":53,"target":10},{"source":39,"target":42},{"source":20,"target":23},{"source":24,"target":32},{"source":38,"target":39},{"source":13,"target":1},{"source":5,"target":51},{"source":21,"target":55},{"source":16,"target":12},{"source":54,"target":22},{"source":36,"target":27},{"source":5,"target":29},{"source":40,"target":6},{"source":32,"target":19},{"source":10,"target":36},{"source":8,"target":50},{"source":13,"target":8},{"source":1,"target":29},{"source":54,"target":15},{"source":37,"target":13},{"source":26,"target":8},{"source":40,"target":46},{"source":4,"target":15},{"source":22,"target":47},{"source":12,"target":21},{"source":22,"target":49},{"source":20,"target":33},{"source":17,"target":4},{"source":1,"target":53},{"source":44,"target":35},{"source":9,"target":0},{"source":14,"target":30},{"source":2,"target":28},{"source":55,"target":47},{"source":42,"target":14},{"source":48,"target":35},{"source":15,"target":33},{"source":5,"target":55},{"source":4,"target":30},{"source":45,"target":23},{"source":12,"target":17},{"source":20,"target":12},{"source":24,"target":37},{"source":30,"target":51},{"source":5,"target":6},{"source":6,"target":24},{"source":12,"target":29},{"source":24,"target":14},{"source":2,"target":22},{"source":6,"target":1},{"source":50,"target":36},{"source":26,"target":18},{"source":4,"target":29},{"source":33,"target":11},{"source":25,"target":4},{"source":42,"target":15},{"source":50,"target":52},{"source":28,"target":38},{"source":8,"target":4},{"source":24,"target":18},{"source":34,"target":46},{"source":55,"target":0},{"source":7,"target":21},{"source":53,"target":51},{"source":25,"target":26},{"source":46,"target":22},{"source":18,"target":7},{"source":43,"target":44},{"source":14,"target":3},{"source":30,"target":22},{"source":21,"target":23},{"source":5,"target":20},{"source":40,"target":30},{"source":17,"target":22},{"source":8,"target":20},{"source":54,"target":47},{"source":47,"target":25},{"source":8,"target":46},{"source":48,"target":40},{"source":2,"target":34},{"source":53,"target":4},{"source":30,"target":35},{"source":49,"target":3},{"source":43,"target":16},{"source":55,"target":18},{"source":29,"target":11},{"source":53,"target":2},{"source":11,"target":35},{"source":55,"target":35},{"source":49,"target":34},{"source":51,"target":22},{"source":45,"target":34},{"source":7,"target":53},{"source":1,"target":43},{"source":55,"target":29},{"source":50,"target":14},{"source":17,"target":50},{"source":17,"target":7},{"source":31,"target":6},{"source":3,"target":48},{"source":0,"target":51},{"source":49,"target":23},{"source":1,"target":46},{"source":23,"target":44},{"source":30,"target":0},{"source":21,"target":47},{"source":31,"target":24},{"source":37,"target":12},{"source":3,"target":36},{"source":7,"target":29},{"source":39,"target":2},{"source":33,"target":18},{"source":45,"target":38},{"source":5,"target":36},{"source":54,"target":12},{"source":17,"target":29},{"source":48,"target":14},{"source":3,"target":15},{"source":5,"target":12},{"source":11,"target":4},{"source":9,"target":42},{"source":46,"target":33},{"source":24,"target":17},{"source":52,"target":0},{"source":44,"target":0},{"source":12,"target":23},{"source":41,"target":51},{"source":35,"target":38},{"source":39,"target":29},{"source":15,"target":40},{"source":8,"target":15},{"source":11,"target":10},{"source":2,"target":7},{"source":39,"target":46},{"source":23,"target":2},{"source":37,"target":45},{"source":15,"target":22},{"source":51,"target":55},{"source":19,"target":41},{"source":1,"target":12},{"source":53,"target":33},{"source":6,"target":4},{"source":46,"target":55},{"source":18,"target":16},{"source":53,"target":12},{"source":26,"target":43},{"source":28,"target":6},{"source":18,"target":36},{"source":34,"target":5},{"source":37,"target":32},{"source":16,"target":9},{"source":22,"target":38},{"source":6,"target":12},{"source":26,"target":54},{"source":7,"target":50},{"source":22,"target":14},{"source":0,"target":24},{"source":44,"target":32},{"source":43,"target":35},{"source":44,"target":31},{"source":34,"target":27},{"source":41,"target":38},{"source":20,"target":3},{"source":38,"target":24},{"source":13,"target":27},{"source":46,"target":21},{"source":13,"target":54},{"source":25,"target":5},{"source":15,"target":6},{"source":3,"target":39},{"source":50,"target":37},{"source":37,"target":48},{"source":39,"target":19},{"source":8,"target":42},{"source":13,"target":28},{"source":50,"target":0},{"source":16,"target":13},{"source":16,"target":14},{"source":34,"target":23},{"source":0,"target":6},{"source":35,"target":40},{"source":22,"target":0},{"source":45,"target":20},{"source":6,"target":35},{"source":48,"target":28},{"source":14,"target":36},{"source":19,"target":14},{"source":22,"target":35},{"source":52,"target":27},{"source":45,"target":5},{"source":1,"target":45},{"source":42,"target":29},{"source":24,"target":11},{"source":29,"target":21},{"source":49,"target":2},{"source":37,"target":47},{"source":14,"target":54},{"source":9,"target":52},{"source":50,"target":45},{"source":46,"target":29},{"source":26,"target":2},{"source":52,"target":5},{"source":54,"target":37},{"source":26,"target":30},{"source":50,"target":34},{"source":32,"target":48},{"source":33,"target":19},{"source":55,"target":28},{"source":6,"target":49},{"source":0,"target":13},{"source":41,"target":11},{"source":29,"target":13},{"source":11,"target":9},{"source":51,"target":40},{"source":46,"target":0},{"source":30,"target":32},{"source":48,"target":10},{"source":49,"target":55},{"source":10,"target":46},{"source":4,"target":54},{"source":42,"target":17},{"source":7,"target":11},{"source":55,"target":48},{"source":19,"target":46},{"source":41,"target":35},{"source":8,"target":29},{"source":2,"target":5},{"source":13,"target":5},{"source":46,"target":35},{"source":25,"target":19},{"source":52,"target":13},{"source":11,"target":14},{"source":53,"target":30},{"source":23,"target":6},{"source":35,"target":54},{"source":36,"target":6},{"source":31,"target":39},{"source":27,"target":2},{"source":23,"target":42},{"source":48,"target":27},{"source":8,"target":49},{"source":8,"target":52},{"source":1,"target":20},{"source":14,"target":28},{"source":51,"target":4},{"source":51,"target":26},{"source":10,"target":47},{"source":53,"target":40},{"source":8,"target":53},{"source":14,"target":15},{"source":27,"target":43},{"source":19,"target":29},{"source":13,"target":55},{"source":49,"target":27},{"source":18,"target":43},{"source":0,"target":3},{"source":26,"target":5},{"source":24,"target":52},{"source":4,"target":42},{"source":51,"target":14},{"source":23,"target":0},{"source":27,"target":5},{"source":1,"target":47},{"source":5,"target":38},{"source":50,"target":9},{"source":29,"target":50},{"source":24,"target":51},{"source":45,"target":3},{"source":32,"target":4},{"source":8,"target":40},{"source":11,"target":44},{"source":38,"target":14},{"source":55,"target":2},{"source":15,"target":39},{"source":4,"target":27},{"source":51,"target":12},{"source":24,"target":26},{"source":20,"target":40},{"source":0,"target":37},{"source":21,"target":39},{"source":22,"target":10},{"source":53,"target":42},{"source":3,"target":8},{"source":22,"target":16},{"source":4,"target":18},{"source":40,"target":42},{"source":5,"target":48},{"source":0,"target":33},{"source":25,"target":54},{"source":28,"target":17},{"source":31,"target":2},{"source":53,"target":23},{"source":35,"target":52},{"source":29,"target":6},{"source":9,"target":54},{"source":15,"target":49},{"source":19,"target":11},{"source":17,"target":46},{"source":40,"target":43},{"source":55,"target":54},{"source":55,"target":33},{"source":55,"target":32},{"source":17,"target":53},{"source":19,"target":36},{"source":7,"target":4},{"source":0,"target":42},{"source":43,"target":28},{"source":53,"target":25},{"source":33,"target":10},{"source":53,"target":43},{"source":9,"target":5},{"source":1,"target":30},{"source":40,"target":52},{"source":31,"target":26},{"source":51,"target":1},{"source":15,"target":45},{"source":42,"target":43},{"source":14,"target":31},{"source":43,"target":22},{"source":26,"target":44},{"source":30,"target":46},{"source":7,"target":33},{"source":32,"target":13},{"source":10,"target":26},{"source":3,"target":51},{"source":24,"target":16},{"source":20,"target":21},{"source":11,"target":0},{"source":33,"target":35},{"source":49,"target":46},{"source":32,"target":29},{"source":4,"target":40},{"source":13,"target":10},{"source":51,"target":17},{"source":37,"target":19},{"source":13,"target":35},{"source":3,"target":10},{"source":38,"target":2},{"source":51,"target":35},{"source":16,"target":23},{"source":2,"target":10},{"source":25,"target":0},{"source":10,"target":38},{"source":46,"target":52},{"source":27,"target":47},{"source":14,"target":17},{"source":49,"target":37},{"source":35,"target":42},{"source":28,"target":30},{"source":10,"target":52},{"source":16,"target":50},{"source":55,"target":1},{"source":15,"target":1},{"source":4,"target":55},{"source":2,"target":8},{"source":36,"target":41},{"source":26,"target":27},{"source":47,"target":14},{"source":9,"target":48},{"source":41,"target":21},{"source":41,"target":45},{"source":16,"target":26},{"source":26,"target":41},{"source":46,"target":37},{"source":8,"target":55},{"source":34,"target":29},{"source":22,"target":44},{"source":12,"target":35},{"source":51,"target":19},{"source":47,"target":42},{"source":50,"target":4},{"source":34,"target":13},{"source":19,"target":26},{"source":48,"target":13},{"source":50,"target":54},{"source":42,"target":10},{"source":9,"target":53},{"source":20,"target":25},{"source":52,"target":34},{"source":43,"target":3},{"source":36,"target":52},{"source":30,"target":20},{"source":38,"target":4},{"source":27,"target":10},{"source":39,"target":10},{"source":20,"target":29},{"source":9,"target":24},{"source":4,"target":3},{"source":34,"target":8},{"source":13,"target":41},{"source":24,"target":29},{"source":35,"target":39},{"source":53,"target":0},{"source":48,"target":0},{"source":2,"target":17},{"source":20,"target":50},{"source":10,"target":9},{"source":44,"target":12},{"source":53,"target":16},{"source":27,"target":38},{"source":55,"target":50},{"source":19,"target":22},{"source":35,"target":25},{"source":3,"target":32},{"source":34,"target":15},{"source":4,"target":41},{"source":41,"target":17},{"source":54,"target":16},{"source":39,"target":16},{"source":9,"target":39},{"source":49,"target":41},{"source":34,"target":1},{"source":36,"target":37},{"source":8,"target":51},{"source":48,"target":6},{"source":43,"target":24},{"source":33,"target":51},{"source":18,"target":1},{"source":7,"target":22},{"source":28,"target":33},{"source":27,"target":31},{"source":45,"target":48},{"source":24,"target":15},{"source":12,"target":49},{"source":7,"target":15},{"source":24,"target":30},{"source":7,"target":40},{"source":43,"target":30},{"source":35,"target":18},{"source":49,"target":10},{"source":13,"target":49},{"source":8,"target":47},{"source":10,"target":40},{"source":26,"target":45},{"source":2,"target":13},{"source":20,"target":14},{"source":19,"target":3},{"source":11,"target":6},{"source":45,"target":9},{"source":24,"target":41},{"source":18,"target":20},{"source":25,"target":37},{"source":10,"target":23},{"source":34,"target":22},{"source":2,"target":11},{"source":7,"target":25},{"source":5,"target":7},{"source":26,"target":13},{"source":36,"target":7},{"source":28,"target":1},{"source":29,"target":10}],"width":1146,"points":[{"x":935,"y":828,"id":0},{"x":807,"y":188,"id":1},{"x":495,"y":528,"id":2},{"x":400,"y":609,"id":3},{"x":404,"y":213,"id":4},{"x":962,"y":712,"id":5},{"x":1113,"y":820,"id":6},{"x":324,"y":777,"id":7},{"x":557,"y":157,"id":8},{"x":646,"y":203,"id":9},{"x":355,"y":434,"id":10},{"x":807,"y":182,"id":11},{"x":920,"y":933,"id":12},{"x":1049,"y":751,"id":13},{"x":1101,"y":714,"id":14},{"x":426,"y":175,"id":15},{"x":290,"y":730,"id":16},{"x":33,"y":916,"id":17},{"x":77,"y":721,"id":18},{"x":389,"y":1046,"id":19},{"x":1140,"y":292,"id":20},{"x":675,"y":684,"id":21},{"x":461,"y":2,"id":22},{"x":274,"y":601,"id":23},{"x":572,"y":143,"id":24},{"x":502,"y":775,"id":25},{"x":991,"y":687,"id":26},{"x":435,"y":624,"id":27},{"x":1026,"y":225,"id":28},{"x":332,"y":996,"id":29},{"x":634,"y":80,"id":30},{"x":759,"y":408,"id":31},{"x":730,"y":719,"id":32},{"x":815,"y":522,"id":33},{"x":658,"y":480,"id":34},{"x":550,"y":795,"id":35},{"x":39,"y":828,"id":36},{"x":1061,"y":103,"id":37},{"x":156,"y":999,"id":38},{"x":448,"y":907,"id":39},{"x":349,"y":438,"id":40},{"x":993,"y":478,"id":41},{"x":1145,"y":509,"id":42},{"x":660,"y":390,"id":43},{"x":853,"y":175,"id":44},{"x":994,"y":435,"id":45},{"x":1048,"y":557,"id":46},{"x":854,"y":405,"id":47},{"x":205,"y":1032,"id":48},{"x":179,"y":262,"id":49},{"x":851,"y":804,"id":50},{"x":970,"y":783,"id":51},{"x":306,"y":191,"id":52},{"x":656,"y":229,"id":53},{"x":572,"y":470,"id":54},{"x":913,"y":455,"id":55},{"x":124,"y":1096,"id":56},{"x":181,"y":196,"id":57},{"x":581,"y":852,"id":58},{"x":629,"y":874,"id":59},{"x":620,"y":830,"id":60},{"x":126,"y":670,"id":61},{"x":447,"y":435,"id":62},{"x":360,"y":1001,"id":63},{"x":303,"y":1014,"id":64},{"x":813,"y":110,"id":65},{"x":114,"y":595,"id":66},{"x":821,"y":150,"id":67},{"x":1073,"y":310,"id":68},{"x":286,"y":15,"id":69},{"x":758,"y":128,"id":70},{"x":874,"y":1068,"id":71},{"x":835,"y":488,"id":72},{"x":865,"y":618,"id":73},{"x":4,"y":503,"id":74},{"x":120,"y":968,"id":75},{"x":678,"y":370,"id":76},{"x":536,"y":592,"id":77},{"x":200,"y":1025,"id":78},{"x":960,"y":498,"id":79},{"x":619,"y":197,"id":80},{"x":602,"y":260,"id":81},{"x":691,"y":572,"id":82},{"x":969,"y":918,"id":83},{"x":757,"y":107,"id":84},{"x":352,"y":647,"id":85},{"x":1027,"y":1018,"id":86},{"x":1141,"y":71,"id":87},{"x":1104,"y":384,"id":88},{"x":361,"y":661,"id":89},{"x":305,"y":226,"id":90},{"x":495,"y":399,"id":91},{"x":29,"y":364,"id":92},{"x":511,"y":878,"id":93},{"x":1018,"y":855,"id":94},{"x":264,"y":199,"id":95},{"x":999,"y":323,"id":96},{"x":237,"y":1045,"id":97},{"x":1133,"y":730,"id":98},{"x":358,"y":574,"id":99},{"x":204,"y":989,"id":100},{"x":495,"y":694,"id":101},{"x":5,"y":970,"id":102},{"x":517,"y":290,"id":103},{"x":229,"y":220,"id":104},{"x":243,"y":957,"id":105},{"x":97,"y":61,"id":106},{"x":178,"y":67,"id":107},{"x":64,"y":54,"id":108},{"x":514,"y":756,"id":109},{"x":250,"y":55,"id":110},{"x":289,"y":625,"id":111},{"x":73,"y":744,"id":112},{"x":718,"y":604,"id":113},{"x":435,"y":800,"id":114},{"x":298,"y":959,"id":115},{"x":642,"y":1116,"id":116},{"x":127,"y":85,"id":117},{"x":419,"y":7,"id":118},{"x":622,"y":597,"id":119},{"x":946,"y":324,"id":120},{"x":1132,"y":285,"id":121},{"x":1001,"y":675,"id":122},{"x":141,"y":724,"id":123},{"x":548,"y":763,"id":124},{"x":1140,"y":153,"id":125},{"x":739,"y":510,"id":126},{"x":1008,"y":1023,"id":127},{"x":310,"y":447,"id":128},{"x":463,"y":248,"id":129},{"x":624,"y":1047,"id":130},{"x":1052,"y":439,"id":131},{"x":396,"y":731,"id":132},{"x":85,"y":326,"id":133},{"x":1090,"y":915,"id":134},{"x":27,"y":735,"id":135},{"x":966,"y":360,"id":136},{"x":479,"y":540,"id":137},{"x":49,"y":1026,"id":138},{"x":279,"y":51,"id":139},{"x":713,"y":518,"id":140},{"x":966,"y":1109,"id":141},{"x":225,"y":133,"id":142},{"x":267,"y":130,"id":143},{"x":326,"y":394,"id":144},{"x":874,"y":803,"id":145},{"x":485,"y":360,"id":146},{"x":866,"y":1082,"id":147},{"x":958,"y":832,"id":148},{"x":360,"y":1135,"id":149},{"x":1138,"y":375,"id":150},{"x":386,"y":200,"id":151},{"x":409,"y":937,"id":152},{"x":468,"y":1086,"id":153},{"x":1139,"y":243,"id":154},{"x":156,"y":725,"id":155},{"x":818,"y":1057,"id":156},{"x":449,"y":683,"id":157},{"x":436,"y":104,"id":158},{"x":611,"y":5,"id":159},{"x":489,"y":0,"id":160},{"x":30,"y":685,"id":161},{"x":234,"y":388,"id":162},{"x":1018,"y":531,"id":163},{"x":676,"y":195,"id":164},{"x":347,"y":1137,"id":165},{"x":728,"y":839,"id":166},{"x":674,"y":21,"id":167}],"height":1146}